cli/__init__.py
cli/cli.py
cli/frpc_manager.py
cli/hook.py
cli/room_config.py
cli/frp_binaries/frpc
cli/frp_binaries/frpc.exe
mact_cli-1.0.9.dist-info/METADATA
mact_cli-1.0.9.dist-info/WHEEL
mact_cli-1.0.9.dist-info/entry_points.txt
mact_cli-1.0.9.dist-info/top_level.txt
mact_cli-1.0.9.dist-info/RECORD
