Metadata-Version: 2.4
Name: mact-cli
Version: 1.0.9
Summary: MACT CLI - Mirrored Active Collaborative Tunnel
Home-page: https://m-act.live
Author: MACT Team
Author-email: 22btcs042hy@manuu.edu.in
License: MIT
Project-URL: Homepage, https://m-act.live
Project-URL: Documentation, https://github.com/mact/mact
Project-URL: Repository, https://github.com/mact/mact
Project-URL: Issues, https://github.com/mact/mact/issues
Keywords: tunnel,development,collaboration,git,frp
Classifier: Development Status :: 4 - Beta
Classifier: Intended Audience :: Developers
Classifier: Topic :: Software Development :: Build Tools
Classifier: License :: OSI Approved :: MIT License
Classifier: Programming Language :: Python :: 3
Classifier: Programming Language :: Python :: 3.8
Classifier: Programming Language :: Python :: 3.9
Classifier: Programming Language :: Python :: 3.10
Classifier: Programming Language :: Python :: 3.11
Classifier: Programming Language :: Python :: 3.12
Requires-Python: >=3.8
Requires-Dist: requests>=2.25.0
Dynamic: author-email
Dynamic: home-page
Dynamic: requires-python
